lemkelcp/lemkelcp.py
lemkelcp/__init__.py
lemkelcp-0.1.dist-info/top_level.txt
lemkelcp-0.1.dist-info/WHEEL
lemkelcp-0.1.dist-info/METADATA
lemkelcp-0.1.dist-info/RECORD
lemkelcp-0.1.dist-info/DESCRIPTION.rst
lemkelcp-0.1.dist-info/metadata.json
